<?xml version='1.0' encoding='UTF-8'?>
<Metadata xmlns="http://www.informatica.com/ilm/pdmds/xml/model" type="Rule" version="10.4.1;null;32;20833">
  <Rule xmlns="http://www.informatica.com/ilm/pdmds/xml/model" active="true" overideAble="true" name="JH_MR_Email_Address" description="JH_Email_Masking" dataType="String" maskingType="EMAIL">
    <RuleParameter name="excp_nullspaceconst" value="false"/>
    <RuleParameter name="errhandling_const" value="false"/>
    <RuleParameter name="errhandling_defser" value="true"/>
    <RuleParameter name="email_seedVal" value="12"/>
    <RuleParameter name="excp_nullspacelogerr" value="false"/>
    <RuleParameter name="excp_trim" value="true"/>
    <RuleParameter name="excp_nullspacedefser" value="false"/>
    <RuleParameter name="excp_nullspaceignore" value="true"/>
    <RuleParameter name="postprocess_expression"/>
    <RuleParameter name="errhandling_ignore" value="false"/>
    <RuleParameter name="errhandling_logexcp" value="false"/>
    <RuleParameter name="email_repeatable" value="true"/>
    <RuleParameter name="errhandling_errout" value="false"/>
    <RuleParameter name="seed_value_is_param" value="false"/>
    <RuleParameter name="email_stdmaskingType" value="true"/>
    <RuleParameter name="email_advmaskingType" value="false"/>
    <RuleParameter name="preprocess_expression"/>
    <RuleParameter name="excp_nullspacetreat" value="false"/>
  </Rule>
  <Rule xmlns="http://www.informatica.com/ilm/pdmds/xml/model" active="true" overideAble="false" name="JH_TRUECOMP_EMAIL" description="If PN=1, Email else if PN=2,No masking">
    <RulePort dataType="String" order="1" scale="255" precision="255" length="0" mandatory="true" portType="INPUT" name="EmailInput"/>
    <RulePort dataType="String" order="4" scale="255" precision="255" length="0" mandatory="true" portType="OUTPUT" expression="Match" name="Outputdata"/>
    <RulePort dataType="Numeric" order="0" scale="10" precision="10" length="0" mandatory="true" portType="INPUT" name="Pagenumber"/>
    <RulePort dataType="String" inputPortName="EmailInput" associatedRuleName="JH_MR_Email_Address" order="2" scale="255" precision="255" length="0" mandatory="true" portType="LOCAL_VARIABLE" name="Email">
      <RulePortParameter name="postprocess_expression" value="UPPER(Input_Column)"/>
      <RulePortParameter name="postprocess_expression" value="UPPER(Input_Column)"/>
      <RulePortParameter name="preprocess_expression" value="UPPER(Input_Column)"/>
      <RulePortParameter name="preprocess_expression" value="UPPER(Input_Column)"/>
      <RulePortParameter name="postprocess_expression" value="UPPER(Input_Column)"/>
      <RulePortParameter name="preprocess_expression" value="UPPER(Input_Column)"/>
    </RulePort>
    <RulePort dataType="String" order="3" scale="255" precision="255" length="0" mandatory="true" portType="LOCAL_VARIABLE" expression="IIF(Pagenumber=1,Email,EmailInput)" name="Match"/>
  </Rule>
</Metadata>